{"data": [{"district": "Thanh Oai", "ward": "Bích Hòa", "street": "Bờ Sông", "city": "Hà Nội", "normalize": "bo song bich hoa thanh oai ha noi", "streetNormalize": "bo song bich hoa thanh oai ha noi", "wardNormalize": "bich hoa thanh oai ha noi", "districtNormalize": "thanh oai ha noi", "preWardNormalize": "xa bich hoa thanh oai ha noi", "lat": 20.9108651, "lon": 105.7616136, "geolocation": {"latitude": 20.9108651, "longitude": 105.7616136}}, {"district": "Thanh Oai", "ward": "Bích Hòa", "street": "Quốc Lộ 21b", "city": "Hà Nội", "normalize": "quoc lo 21b bich hoa thanh oai ha noi", "streetNormalize": "quoc lo 21b bich hoa thanh oai ha noi", "wardNormalize": "bich hoa thanh oai ha noi", "districtNormalize": "thanh oai ha noi", "preWardNormalize": "xa bich hoa thanh oai ha noi", "lat": 20.9181141, "lon": 105.7590604, "geolocation": {"latitude": 20.9181141, "longitude": 105.7590604}}, {"district": "Thanh Oai", "ward": "Bích Hòa", "street": "Thạch Bích", "city": "Hà Nội", "normalize": "thach bich bich hoa thanh oai ha noi", "streetNormalize": "thach bich bich hoa thanh oai ha noi", "wardNormalize": "bich hoa thanh oai ha noi", "districtNormalize": "thanh oai ha noi", "preWardNormalize": "xa bich hoa thanh oai ha noi", "lat": 20.9199261, "lon": 105.759853, "geolocation": {"latitude": 20.9199261, "longitude": 105.759853}}, {"district": "Thanh Oai", "ward": "Bích Hòa", "street": "Đồng Dương", "city": "Hà Nội", "normalize": "dong duong bich hoa thanh oai ha noi", "streetNormalize": "dong duong bich hoa thanh oai ha noi", "wardNormalize": "bich hoa thanh oai ha noi", "districtNormalize": "thanh oai ha noi", "preWardNormalize": "xa bich hoa thanh oai ha noi", "lat": 20.9235747, "lon": 105.7531062, "geolocation": {"latitude": 20.9235747, "longitude": 105.7531062}}, {"district": "Thanh Oai", "ward": "Bình Minh", "street": "10/3", "city": "Hà Nội", "normalize": "10/3 binh minh thanh oai ha noi", "streetNormalize": "10/3 binh minh thanh oai ha noi", "wardNormalize": "binh minh thanh oai ha noi", "districtNormalize": "thanh oai ha noi", "preWardNormalize": "xa binh minh thanh oai ha noi", "lat": 20.8886959474962, "lon": 105.761840975898, "geolocation": {"latitude": 20.8886959474962, "longitude": 105.761840975898}}, {"district": "Thanh Oai", "ward": "Bình Minh", "street": "3/2", "city": "Hà Nội", "normalize": "3/2 binh minh thanh oai ha noi", "streetNormalize": "3/2 binh minh thanh oai ha noi", "wardNormalize": "binh minh thanh oai ha noi", "districtNormalize": "thanh oai ha noi", "preWardNormalize": "xa binh minh thanh oai ha noi", "lat": 20.8935718, "lon": 105.7810158, "geolocation": {"latitude": 20.8935718, "longitude": 105.7810158}}, {"district": "Thanh Oai", "ward": "Bình Minh", "street": "8/3", "city": "Hà Nội", "normalize": "8/3 binh minh thanh oai ha noi", "streetNormalize": "8/3 binh minh thanh oai ha noi", "wardNormalize": "binh minh thanh oai ha noi", "districtNormalize": "thanh oai ha noi", "preWardNormalize": "xa binh minh thanh oai ha noi", "lat": 20.8892634, "lon": 105.7657733, "geolocation": {"latitude": 20.8892634, "longitude": 105.7657733}}, {"district": "Thanh Oai", "ward": "Bình Minh", "street": "Ao Lấp", "city": "Hà Nội", "normalize": "ao lap binh minh thanh oai ha noi", "streetNormalize": "ao lap binh minh thanh oai ha noi", "wardNormalize": "binh minh thanh oai ha noi", "districtNormalize": "thanh oai ha noi", "preWardNormalize": "xa binh minh thanh oai ha noi", "lat": 20.893557, "lon": 105.7799242, "geolocation": {"latitude": 20.893557, "longitude": 105.7799242}}, {"district": "Thanh Oai", "ward": "Bình Minh", "street": "Bình Minh", "city": "Hà Nội", "normalize": "binh minh binh minh thanh oai ha noi", "streetNormalize": "binh minh binh minh thanh oai ha noi", "wardNormalize": "binh minh thanh oai ha noi", "districtNormalize": "thanh oai ha noi", "preWardNormalize": "xa binh minh thanh oai ha noi", "lat": 20.8931173, "lon": 105.7733848, "geolocation": {"latitude": 20.8931173, "longitude": 105.7733848}}, {"district": "Thanh Oai", "ward": "Bình Minh", "street": "Bình Minh 2", "city": "Hà Nội", "normalize": "binh minh 2 binh minh thanh oai ha noi", "streetNormalize": "binh minh 2 binh minh thanh oai ha noi", "wardNormalize": "binh minh thanh oai ha noi", "districtNormalize": "thanh oai ha noi", "preWardNormalize": "xa binh minh thanh oai ha noi", "lat": 20.901248, "lon": 105.7661999, "geolocation": {"latitude": 20.901248, "longitude": 105.7661999}}, {"district": "Thanh Oai", "ward": "Bình Minh", "street": "Bảo Đà", "city": "Hà Nội", "normalize": "bao da binh minh thanh oai ha noi", "streetNormalize": "bao da binh minh thanh oai ha noi", "wardNormalize": "binh minh thanh oai ha noi", "districtNormalize": "thanh oai ha noi", "preWardNormalize": "xa binh minh thanh oai ha noi", "lat": 20.8984757, "lon": 105.765742, "geolocation": {"latitude": 20.8984757, "longitude": 105.765742}}, {"district": "Thanh Oai", "ward": "Bình Minh", "street": "Chân Thánh", "city": "Hà Nội", "normalize": "chan thanh binh minh thanh oai ha noi", "streetNormalize": "chan thanh binh minh thanh oai ha noi", "wardNormalize": "binh minh thanh oai ha noi", "districtNormalize": "thanh oai ha noi", "preWardNormalize": "xa binh minh thanh oai ha noi", "lat": 20.8933071, "lon": 105.7676085, "geolocation": {"latitude": 20.8933071, "longitude": 105.7676085}}, {"district": "Thanh Oai", "ward": "Bình Minh", "street": "Cây Dừa", "city": "Hà Nội", "normalize": "cay dua binh minh thanh oai ha noi", "streetNormalize": "cay dua binh minh thanh oai ha noi", "wardNormalize": "binh minh thanh oai ha noi", "districtNormalize": "thanh oai ha noi", "preWardNormalize": "xa binh minh thanh oai ha noi", "lat": 20.8926474, "lon": 105.7746002, "geolocation": {"latitude": 20.8926474, "longitude": 105.7746002}}, {"district": "Thanh Oai", "ward": "Bình Minh", "street": "Cổng Cầu", "city": "Hà Nội", "normalize": "cong cau binh minh thanh oai ha noi", "streetNormalize": "cong cau binh minh thanh oai ha noi", "wardNormalize": "binh minh thanh oai ha noi", "districtNormalize": "thanh oai ha noi", "preWardNormalize": "xa binh minh thanh oai ha noi", "lat": 20.8924465, "lon": 105.774126, "geolocation": {"latitude": 20.8924465, "longitude": 105.774126}}, {"district": "Thanh Oai", "ward": "Bình Minh", "street": "Cổng Đồn", "city": "Hà Nội", "normalize": "cong don binh minh thanh oai ha noi", "streetNormalize": "cong don binh minh thanh oai ha noi", "wardNormalize": "binh minh thanh oai ha noi", "districtNormalize": "thanh oai ha noi", "preWardNormalize": "xa binh minh thanh oai ha noi", "lat": 20.8929752, "lon": 105.7799606, "geolocation": {"latitude": 20.8929752, "longitude": 105.7799606}}, {"district": "Thanh Oai", "ward": "Bình Minh", "street": "Hùng Vương", "city": "Hà Nội", "normalize": "hung vuong binh minh thanh oai ha noi", "streetNormalize": "hung vuong binh minh thanh oai ha noi", "wardNormalize": "binh minh thanh oai ha noi", "districtNormalize": "thanh oai ha noi", "preWardNormalize": "xa binh minh thanh oai ha noi", "lat": 20.8942823, "lon": 105.7693896, "geolocation": {"latitude": 20.8942823, "longitude": 105.7693896}}, {"district": "Thanh Oai", "ward": "Bình Minh", "street": "Lạc Long Quân", "city": "Hà Nội", "normalize": "lac long quan binh minh thanh oai ha noi", "streetNormalize": "lac long quan binh minh thanh oai ha noi", "wardNormalize": "binh minh thanh oai ha noi", "districtNormalize": "thanh oai ha noi", "preWardNormalize": "xa binh minh thanh oai ha noi", "lat": 20.8950442, "lon": 105.7658643, "geolocation": {"latitude": 20.8950442, "longitude": 105.7658643}}, {"district": "Thanh Oai", "ward": "Bình Minh", "street": "Minh Kha", "city": "Hà Nội", "normalize": "minh kha binh minh thanh oai ha noi", "streetNormalize": "minh kha binh minh thanh oai ha noi", "wardNormalize": "binh minh thanh oai ha noi", "districtNormalize": "thanh oai ha noi", "preWardNormalize": "xa binh minh thanh oai ha noi", "lat": 20.8916059, "lon": 105.7808374, "geolocation": {"latitude": 20.8916059, "longitude": 105.7808374}}, {"district": "Thanh Oai", "ward": "Bình Minh", "street": "Minh Sinh", "city": "Hà Nội", "normalize": "minh sinh binh minh thanh oai ha noi", "streetNormalize": "minh sinh binh minh thanh oai ha noi", "wardNormalize": "binh minh thanh oai ha noi", "districtNormalize": "thanh oai ha noi", "preWardNormalize": "xa binh minh thanh oai ha noi", "lat": 20.8926988, "lon": 105.7756324, "geolocation": {"latitude": 20.8926988, "longitude": 105.7756324}}, {"district": "Thanh Oai", "ward": "Bình Minh", "street": "Ngô Long", "city": "Hà Nội", "normalize": "ngo long binh minh thanh oai ha noi", "streetNormalize": "ngo long binh minh thanh oai ha noi", "wardNormalize": "binh minh thanh oai ha noi", "districtNormalize": "thanh oai ha noi", "preWardNormalize": "xa binh minh thanh oai ha noi", "lat": 20.8907729, "lon": 105.772558, "geolocation": {"latitude": 20.8907729, "longitude": 105.772558}}, {"district": "Thanh Oai", "ward": "Bình Minh", "street": "Ngõ Cá", "city": "Hà Nội", "normalize": "ngo ca binh minh thanh oai ha noi", "streetNormalize": "ngo ca binh minh thanh oai ha noi", "wardNormalize": "binh minh thanh oai ha noi", "districtNormalize": "thanh oai ha noi", "preWardNormalize": "xa binh minh thanh oai ha noi", "lat": 20.8920351, "lon": 105.7803609, "geolocation": {"latitude": 20.8920351, "longitude": 105.7803609}}, {"district": "Thanh Oai", "ward": "Bình Minh", "street": "Ngõ Giếng", "city": "Hà Nội", "normalize": "ngo gieng binh minh thanh oai ha noi", "streetNormalize": "ngo gieng binh minh thanh oai ha noi", "wardNormalize": "binh minh thanh oai ha noi", "districtNormalize": "thanh oai ha noi", "preWardNormalize": "xa binh minh thanh oai ha noi", "lat": 20.8929739, "lon": 105.7787538, "geolocation": {"latitude": 20.8929739, "longitude": 105.7787538}}, {"district": "Thanh Oai", "ward": "Bình Minh", "street": "Phạm Ngũ Lão", "city": "Hà Nội", "normalize": "pham ngu lao binh minh thanh oai ha noi", "streetNormalize": "pham ngu lao binh minh thanh oai ha noi", "wardNormalize": "binh minh thanh oai ha noi", "districtNormalize": "thanh oai ha noi", "preWardNormalize": "xa binh minh thanh oai ha noi", "lat": 20.8943095, "lon": 105.7788131, "geolocation": {"latitude": 20.8943095, "longitude": 105.7788131}}, {"district": "Thanh Oai", "ward": "Bình Minh", "street": "Phạm Văn Đồng", "city": "Hà Nội", "normalize": "pham van dong binh minh thanh oai ha noi", "streetNormalize": "pham van dong binh minh thanh oai ha noi", "wardNormalize": "binh minh thanh oai ha noi", "districtNormalize": "thanh oai ha noi", "preWardNormalize": "xa binh minh thanh oai ha noi", "lat": 20.8976397, "lon": 105.7705772, "geolocation": {"latitude": 20.8976397, "longitude": 105.7705772}}, {"district": "Thanh Oai", "ward": "Bình Minh", "street": "Quốc Lộ 21b", "city": "Hà Nội", "normalize": "quoc lo 21b binh minh thanh oai ha noi", "streetNormalize": "quoc lo 21b binh minh thanh oai ha noi", "wardNormalize": "binh minh thanh oai ha noi", "districtNormalize": "thanh oai ha noi", "preWardNormalize": "xa binh minh thanh oai ha noi", "lat": 20.8906329, "lon": 105.7636742, "geolocation": {"latitude": 20.8906329, "longitude": 105.7636742}}, {"district": "Thanh Oai", "ward": "Bình Minh", "street": "Sinh Quả", "city": "Hà Nội", "normalize": "sinh qua binh minh thanh oai ha noi", "streetNormalize": "sinh qua binh minh thanh oai ha noi", "wardNormalize": "binh minh thanh oai ha noi", "districtNormalize": "thanh oai ha noi", "preWardNormalize": "xa binh minh thanh oai ha noi", "lat": 20.8898217, "lon": 105.7711738, "geolocation": {"latitude": 20.8898217, "longitude": 105.7711738}}, {"district": "Thanh Oai", "ward": "Bình Minh", "street": "Thanh Quả", "city": "Hà Nội", "normalize": "thanh qua binh minh thanh oai ha noi", "streetNormalize": "thanh qua binh minh thanh oai ha noi", "wardNormalize": "binh minh thanh oai ha noi", "districtNormalize": "thanh oai ha noi", "preWardNormalize": "xa binh minh thanh oai ha noi", "lat": 20.889633, "lon": 105.7728081, "geolocation": {"latitude": 20.889633, "longitude": 105.7728081}}, {"district": "Thanh Oai", "ward": "Bình Minh", "street": "Thành Quách 1", "city": "Hà Nội", "normalize": "thanh quach 1 binh minh thanh oai ha noi", "streetNormalize": "thanh quach 1 binh minh thanh oai ha noi", "wardNormalize": "binh minh thanh oai ha noi", "districtNormalize": "thanh oai ha noi", "preWardNormalize": "xa binh minh thanh oai ha noi", "lat": 20.8949163, "lon": 105.76766, "geolocation": {"latitude": 20.8949163, "longitude": 105.76766}}, {"district": "Thanh Oai", "ward": "Bình Minh", "street": "Thành Quách 2", "city": "Hà Nội", "normalize": "thanh quach 2 binh minh thanh oai ha noi", "streetNormalize": "thanh quach 2 binh minh thanh oai ha noi", "wardNormalize": "binh minh thanh oai ha noi", "districtNormalize": "thanh oai ha noi", "preWardNormalize": "xa binh minh thanh oai ha noi", "lat": 20.8958517, "lon": 105.7679282, "geolocation": {"latitude": 20.8958517, "longitude": 105.7679282}}, {"district": "Thanh Oai", "ward": "Bình Minh", "street": "Thắng Lợi", "city": "Hà Nội", "normalize": "thang loi binh minh thanh oai ha noi", "streetNormalize": "thang loi binh minh thanh oai ha noi", "wardNormalize": "binh minh thanh oai ha noi", "districtNormalize": "thanh oai ha noi", "preWardNormalize": "xa binh minh thanh oai ha noi", "lat": 20.9017412, "lon": 105.7609879, "geolocation": {"latitude": 20.9017412, "longitude": 105.7609879}}, {"district": "Thanh Oai", "ward": "Bình Minh", "street": "Tê Quả", "city": "Hà Nội", "normalize": "te qua binh minh thanh oai ha noi", "streetNormalize": "te qua binh minh thanh oai ha noi", "wardNormalize": "binh minh thanh oai ha noi", "districtNormalize": "thanh oai ha noi", "preWardNormalize": "xa binh minh thanh oai ha noi", "lat": 20.8903817, "lon": 105.7751969, "geolocation": {"latitude": 20.8903817, "longitude": 105.7751969}}, {"district": "Thanh Oai", "ward": "Bình Minh", "street": "Vườn Trũng", "city": "Hà Nội", "normalize": "vuon trung binh minh thanh oai ha noi", "streetNormalize": "vuon trung binh minh thanh oai ha noi", "wardNormalize": "binh minh thanh oai ha noi", "districtNormalize": "thanh oai ha noi", "preWardNormalize": "xa binh minh thanh oai ha noi", "lat": 20.8918274, "lon": 105.7722115, "geolocation": {"latitude": 20.8918274, "longitude": 105.7722115}}, {"district": "Thanh Oai", "ward": "Bình Minh", "street": "Xóm Cây Thị", "city": "Hà Nội", "normalize": "xom cay thi binh minh thanh oai ha noi", "streetNormalize": "xom cay thi binh minh thanh oai ha noi", "wardNormalize": "binh minh thanh oai ha noi", "districtNormalize": "thanh oai ha noi", "preWardNormalize": "xa binh minh thanh oai ha noi", "lat": 20.8918802, "lon": 105.7732422, "geolocation": {"latitude": 20.8918802, "longitude": 105.7732422}}, {"district": "Thanh Oai", "ward": "Bình Minh", "street": "Xóm Lầy", "city": "Hà Nội", "normalize": "xom lay binh minh thanh oai ha noi", "streetNormalize": "xom lay binh minh thanh oai ha noi", "wardNormalize": "binh minh thanh oai ha noi", "districtNormalize": "thanh oai ha noi", "preWardNormalize": "xa binh minh thanh oai ha noi", "lat": 20.8914596, "lon": 105.7745466, "geolocation": {"latitude": 20.8914596, "longitude": 105.7745466}}, {"district": "Thanh Oai", "ward": "Bình Minh", "street": "Xóm Sau", "city": "Hà Nội", "normalize": "xom sau binh minh thanh oai ha noi", "streetNormalize": "xom sau binh minh thanh oai ha noi", "wardNormalize": "binh minh thanh oai ha noi", "districtNormalize": "thanh oai ha noi", "preWardNormalize": "xa binh minh thanh oai ha noi", "lat": 20.8923764, "lon": 105.7726589, "geolocation": {"latitude": 20.8923764, "longitude": 105.7726589}}, {"district": "Thanh Oai", "ward": "Bình Minh", "street": "Âu Cơ", "city": "Hà Nội", "normalize": "au co binh minh thanh oai ha noi", "streetNormalize": "au co binh minh thanh oai ha noi", "wardNormalize": "binh minh thanh oai ha noi", "districtNormalize": "thanh oai ha noi", "preWardNormalize": "xa binh minh thanh oai ha noi", "lat": 20.8930205, "lon": 105.7662473, "geolocation": {"latitude": 20.8930205, "longitude": 105.7662473}}, {"district": "Thanh Oai", "ward": "Bình Minh", "street": "Đt 427b", "city": "Hà Nội", "normalize": "dt 427b binh minh thanh oai ha noi", "streetNormalize": "dt 427b binh minh thanh oai ha noi", "wardNormalize": "binh minh thanh oai ha noi", "districtNormalize": "thanh oai ha noi", "preWardNormalize": "xa binh minh thanh oai ha noi", "lat": 20.8881768, "lon": 105.7677502, "geolocation": {"latitude": 20.8881768, "longitude": 105.7677502}}, {"district": "Thanh Oai", "ward": "Bình Minh", "street": "Đìa 1", "city": "Hà Nội", "normalize": "dia 1 binh minh thanh oai ha noi", "streetNormalize": "dia 1 binh minh thanh oai ha noi", "wardNormalize": "binh minh thanh oai ha noi", "districtNormalize": "thanh oai ha noi", "preWardNormalize": "xa binh minh thanh oai ha noi", "lat": 20.896889, "lon": 105.7676954, "geolocation": {"latitude": 20.896889, "longitude": 105.7676954}}, {"district": "Thanh Oai", "ward": "Bình Minh", "street": "Đìa 2", "city": "Hà Nội", "normalize": "dia 2 binh minh thanh oai ha noi", "streetNormalize": "dia 2 binh minh thanh oai ha noi", "wardNormalize": "binh minh thanh oai ha noi", "districtNormalize": "thanh oai ha noi", "preWardNormalize": "xa binh minh thanh oai ha noi", "lat": 20.8972365, "lon": 105.766188, "geolocation": {"latitude": 20.8972365, "longitude": 105.766188}}, {"district": "Thanh Oai", "ward": "Cao Dương", "street": "Đt 429", "city": "Hà Nội", "normalize": "dt 429 cao duong thanh oai ha noi", "streetNormalize": "dt 429 cao duong thanh oai ha noi", "wardNormalize": "cao duong thanh oai ha noi", "districtNormalize": "thanh oai ha noi", "preWardNormalize": "xa cao duong thanh oai ha noi", "lat": 20.8132311, "lon": 105.7598119, "geolocation": {"latitude": 20.8132311, "longitude": 105.7598119}}, {"district": "Thanh Oai", "ward": "Cao Dương", "street": "Đê Tả Đáy", "city": "Hà Nội", "normalize": "de ta day cao duong thanh oai ha noi", "streetNormalize": "de ta day cao duong thanh oai ha noi", "wardNormalize": "cao duong thanh oai ha noi", "districtNormalize": "thanh oai ha noi", "preWardNormalize": "xa cao duong thanh oai ha noi", "lat": 20.8201379, "lon": 105.7603973, "geolocation": {"latitude": 20.8201379, "longitude": 105.7603973}}, {"district": "Thanh Oai", "ward": "Cao Viên", "street": "Bờ Sông", "city": "Hà Nội", "normalize": "bo song cao vien thanh oai ha noi", "streetNormalize": "bo song cao vien thanh oai ha noi", "wardNormalize": "cao vien thanh oai ha noi", "districtNormalize": "thanh oai ha noi", "preWardNormalize": "xa cao vien thanh oai ha noi", "lat": 20.907535, "lon": 105.7528295, "geolocation": {"latitude": 20.907535, "longitude": 105.7528295}}, {"district": "Thanh Oai", "ward": "Cao Viên", "street": "Liên Thôn", "city": "Hà Nội", "normalize": "lien thon cao vien thanh oai ha noi", "streetNormalize": "lien thon cao vien thanh oai ha noi", "wardNormalize": "cao vien thanh oai ha noi", "districtNormalize": "thanh oai ha noi", "preWardNormalize": "xa cao vien thanh oai ha noi", "lat": 20.903734, "lon": 105.7422056, "geolocation": {"latitude": 20.903734, "longitude": 105.7422056}}, {"district": "Thanh Oai", "ward": "Cao Viên", "street": "Quan Âm", "city": "Hà Nội", "normalize": "quan am cao vien thanh oai ha noi", "streetNormalize": "quan am cao vien thanh oai ha noi", "wardNormalize": "cao vien thanh oai ha noi", "districtNormalize": "thanh oai ha noi", "preWardNormalize": "xa cao vien thanh oai ha noi", "lat": 20.9056531, "lon": 105.74433, "geolocation": {"latitude": 20.9056531, "longitude": 105.74433}}, {"district": "Thanh Oai", "ward": "Cao Viên", "street": "Thắng Lợi", "city": "Hà Nội", "normalize": "thang loi cao vien thanh oai ha noi", "streetNormalize": "thang loi cao vien thanh oai ha noi", "wardNormalize": "cao vien thanh oai ha noi", "districtNormalize": "thanh oai ha noi", "preWardNormalize": "xa cao vien thanh oai ha noi", "lat": 20.8974917, "lon": 105.754922, "geolocation": {"latitude": 20.8974917, "longitude": 105.754922}}, {"district": "Thanh Oai", "ward": "Cao Viên", "street": "Xóm Biêu", "city": "Hà Nội", "normalize": "xom bieu cao vien thanh oai ha noi", "streetNormalize": "xom bieu cao vien thanh oai ha noi", "wardNormalize": "cao vien thanh oai ha noi", "districtNormalize": "thanh oai ha noi", "preWardNormalize": "xa cao vien thanh oai ha noi", "lat": 20.9047959, "lon": 105.7438337, "geolocation": {"latitude": 20.9047959, "longitude": 105.7438337}}, {"district": "Thanh Oai", "ward": "Cao Viên", "street": "Xóm Côn", "city": "Hà Nội", "normalize": "xom con cao vien thanh oai ha noi", "streetNormalize": "xom con cao vien thanh oai ha noi", "wardNormalize": "cao vien thanh oai ha noi", "districtNormalize": "thanh oai ha noi", "preWardNormalize": "xa cao vien thanh oai ha noi", "lat": 20.9086823, "lon": 105.740551, "geolocation": {"latitude": 20.9086823, "longitude": 105.740551}}, {"district": "Thanh Oai", "ward": "Cao Viên", "street": "Xóm Giữa Thôn Vỹ", "city": "Hà Nội", "normalize": "xom giua thon vy cao vien thanh oai ha noi", "streetNormalize": "xom giua thon vy cao vien thanh oai ha noi", "wardNormalize": "cao vien thanh oai ha noi", "districtNormalize": "thanh oai ha noi", "preWardNormalize": "xa cao vien thanh oai ha noi", "lat": 20.9052344, "lon": 105.7436269, "geolocation": {"latitude": 20.9052344, "longitude": 105.7436269}}, {"district": "Thanh Oai", "ward": "Cao Viên", "street": "Xóm Âm", "city": "Hà Nội", "normalize": "xom am cao vien thanh oai ha noi", "streetNormalize": "xom am cao vien thanh oai ha noi", "wardNormalize": "cao vien thanh oai ha noi", "districtNormalize": "thanh oai ha noi", "preWardNormalize": "xa cao vien thanh oai ha noi", "lat": 20.9036253, "lon": 105.7457049, "geolocation": {"latitude": 20.9036253, "longitude": 105.7457049}}, {"district": "Thanh Oai", "ward": "Cao Viên", "street": "Xóm Đậu Thôn Vỹ", "city": "Hà Nội", "normalize": "xom dau thon vy cao vien thanh oai ha noi", "streetNormalize": "xom dau thon vy cao vien thanh oai ha noi", "wardNormalize": "cao vien thanh oai ha noi", "districtNormalize": "thanh oai ha noi", "preWardNormalize": "xa cao vien thanh oai ha noi", "lat": 20.9053096, "lon": 105.742715, "geolocation": {"latitude": 20.9053096, "longitude": 105.742715}}, {"district": "Thanh Oai", "ward": "Cao Viên", "street": "Đê Tả Đáy", "city": "Hà Nội", "normalize": "de ta day cao vien thanh oai ha noi", "streetNormalize": "de ta day cao vien thanh oai ha noi", "wardNormalize": "cao vien thanh oai ha noi", "districtNormalize": "thanh oai ha noi", "preWardNormalize": "xa cao vien thanh oai ha noi", "lat": 20.8622941, "lon": 105.7444443, "geolocation": {"latitude": 20.8622941, "longitude": 105.7444443}}, {"district": "Thanh Oai", "ward": "Cao Viên", "street": "Đường Mương", "city": "Hà Nội", "normalize": "duong muong cao vien thanh oai ha noi", "streetNormalize": "duong muong cao vien thanh oai ha noi", "wardNormalize": "cao vien thanh oai ha noi", "districtNormalize": "thanh oai ha noi", "preWardNormalize": "xa cao vien thanh oai ha noi", "lat": 20.9038792, "lon": 105.7494806, "geolocation": {"latitude": 20.9038792, "longitude": 105.7494806}}, {"district": "Thanh Oai", "ward": "Cự Khê", "street": "Bờ Sông", "city": "Hà Nội", "normalize": "bo song cu khe thanh oai ha noi", "streetNormalize": "bo song cu khe thanh oai ha noi", "wardNormalize": "cu khe thanh oai ha noi", "districtNormalize": "thanh oai ha noi", "preWardNormalize": "xa cu khe thanh oai ha noi", "lat": 20.9207905, "lon": 105.7800324, "geolocation": {"latitude": 20.9207905, "longitude": 105.7800324}}, {"district": "Thanh Oai", "ward": "Cự Khê", "street": "Hữu Hòa", "city": "Hà Nội", "normalize": "huu hoa cu khe thanh oai ha noi", "streetNormalize": "huu hoa cu khe thanh oai ha noi", "wardNormalize": "cu khe thanh oai ha noi", "districtNormalize": "thanh oai ha noi", "preWardNormalize": "xa cu khe thanh oai ha noi", "lat": 20.928704, "lon": 105.7935734, "geolocation": {"latitude": 20.928704, "longitude": 105.7935734}}, {"district": "Thanh Oai", "ward": "Cự Khê", "street": "Đường Sái", "city": "Hà Nội", "normalize": "duong sai cu khe thanh oai ha noi", "streetNormalize": "duong sai cu khe thanh oai ha noi", "wardNormalize": "cu khe thanh oai ha noi", "districtNormalize": "thanh oai ha noi", "preWardNormalize": "xa cu khe thanh oai ha noi", "lat": 20.9043491, "lon": 105.785964, "geolocation": {"latitude": 20.9043491, "longitude": 105.785964}}, {"district": "Thanh Oai", "ward": "Cự Khê", "street": "Đường Trục Phía Nam", "city": "Hà Nội", "normalize": "duong truc phia nam cu khe thanh oai ha noi", "streetNormalize": "duong truc phia nam cu khe thanh oai ha noi", "wardNormalize": "cu khe thanh oai ha noi", "districtNormalize": "thanh oai ha noi", "preWardNormalize": "xa cu khe thanh oai ha noi", "lat": 20.9155439, "lon": 105.7844503, "geolocation": {"latitude": 20.9155439, "longitude": 105.7844503}}, {"district": "Thanh Oai", "ward": "Dân Hòa", "street": "Liên Thôn Xã", "city": "Hà Nội", "normalize": "lien thon xa dan hoa thanh oai ha noi", "streetNormalize": "lien thon xa dan hoa thanh oai ha noi", "wardNormalize": "dan hoa thanh oai ha noi", "districtNormalize": "thanh oai ha noi", "preWardNormalize": "xa dan hoa thanh oai ha noi", "lat": 20.8143053, "lon": 105.7876262, "geolocation": {"latitude": 20.8143053, "longitude": 105.7876262}}, {"district": "Thanh Oai", "ward": "Dân Hòa", "street": "Quốc Lộ 21b", "city": "Hà Nội", "normalize": "quoc lo 21b dan hoa thanh oai ha noi", "streetNormalize": "quoc lo 21b dan hoa thanh oai ha noi", "wardNormalize": "dan hoa thanh oai ha noi", "districtNormalize": "thanh oai ha noi", "preWardNormalize": "xa dan hoa thanh oai ha noi", "lat": 20.812278, "lon": 105.7760458, "geolocation": {"latitude": 20.812278, "longitude": 105.7760458}}, {"district": "Thanh Oai", "ward": "Dân Hòa", "street": "Đt 429", "city": "Hà Nội", "normalize": "dt 429 dan hoa thanh oai ha noi", "streetNormalize": "dt 429 dan hoa thanh oai ha noi", "wardNormalize": "dan hoa thanh oai ha noi", "districtNormalize": "thanh oai ha noi", "preWardNormalize": "xa dan hoa thanh oai ha noi", "lat": 20.8115463, "lon": 105.7717423, "geolocation": {"latitude": 20.8115463, "longitude": 105.7717423}}, {"district": "Thanh Oai", "ward": "Hồng Dương", "street": "Quốc Lộ 21b", "city": "Hà Nội", "normalize": "quoc lo 21b hong duong thanh oai ha noi", "streetNormalize": "quoc lo 21b hong duong thanh oai ha noi", "wardNormalize": "hong duong thanh oai ha noi", "districtNormalize": "thanh oai ha noi", "preWardNormalize": "xa hong duong thanh oai ha noi", "lat": 20.853637, "lon": 105.7684941, "geolocation": {"latitude": 20.853637, "longitude": 105.7684941}}, {"district": "Thanh Oai", "ward": "Hồng Dương", "street": "Đường Trục Phía Nam", "city": "Hà Nội", "normalize": "duong truc phia nam hong duong thanh oai ha noi", "streetNormalize": "duong truc phia nam hong duong thanh oai ha noi", "wardNormalize": "hong duong thanh oai ha noi", "districtNormalize": "thanh oai ha noi", "preWardNormalize": "xa hong duong thanh oai ha noi", "lat": 20.8495625, "lon": 105.8022895, "geolocation": {"latitude": 20.8495625, "longitude": 105.8022895}}, {"district": "Thanh Oai", "ward": "Kim An", "street": "Đê Tả Đáy", "city": "Hà Nội", "normalize": "de ta day kim an thanh oai ha noi", "streetNormalize": "de ta day kim an thanh oai ha noi", "wardNormalize": "kim an thanh oai ha noi", "districtNormalize": "thanh oai ha noi", "preWardNormalize": "xa kim an thanh oai ha noi", "lat": 20.8622941, "lon": 105.7444443, "geolocation": {"latitude": 20.8622941, "longitude": 105.7444443}}, {"district": "Thanh Oai", "ward": "Kim Bài", "street": "Quốc Lộ 21b", "city": "Hà Nội", "normalize": "quoc lo 21b kim bai thanh oai ha noi", "streetNormalize": "quoc lo 21b kim bai thanh oai ha noi", "wardNormalize": "kim bai thanh oai ha noi", "districtNormalize": "thanh oai ha noi", "preWardNormalize": "thi tran kim bai thanh oai ha noi", "lat": 20.8537224, "lon": 105.7684022, "geolocation": {"latitude": 20.8537224, "longitude": 105.7684022}}, {"district": "Thanh Oai", "ward": "Kim Bài", "street": "Đê Tả Đáy", "city": "Hà Nội", "normalize": "de ta day kim bai thanh oai ha noi", "streetNormalize": "de ta day kim bai thanh oai ha noi", "wardNormalize": "kim bai thanh oai ha noi", "districtNormalize": "thanh oai ha noi", "preWardNormalize": "thi tran kim bai thanh oai ha noi", "lat": 20.8622941, "lon": 105.7444443, "geolocation": {"latitude": 20.8622941, "longitude": 105.7444443}}, {"district": "Thanh Oai", "ward": "Kim Bài", "street": "Đường Muỗi", "city": "Hà Nội", "normalize": "duong muoi kim bai thanh oai ha noi", "streetNormalize": "duong muoi kim bai thanh oai ha noi", "wardNormalize": "kim bai thanh oai ha noi", "districtNormalize": "thanh oai ha noi", "preWardNormalize": "thi tran kim bai thanh oai ha noi", "lat": 20.8593675, "lon": 105.773894, "geolocation": {"latitude": 20.8593675, "longitude": 105.773894}}, {"district": "Thanh Oai", "ward": "Kim Thư", "street": "Quốc Lộ 21b", "city": "Hà Nội", "normalize": "quoc lo 21b kim thu thanh oai ha noi", "streetNormalize": "quoc lo 21b kim thu thanh oai ha noi", "wardNormalize": "kim thu thanh oai ha noi", "districtNormalize": "thanh oai ha noi", "preWardNormalize": "xa kim thu thanh oai ha noi", "lat": 20.853637, "lon": 105.7684941, "geolocation": {"latitude": 20.853637, "longitude": 105.7684941}}, {"district": "Thanh Oai", "ward": "Kim Thư", "street": "Xóm 4", "city": "Hà Nội", "normalize": "xom 4 kim thu thanh oai ha noi", "streetNormalize": "xom 4 kim thu thanh oai ha noi", "wardNormalize": "kim thu thanh oai ha noi", "districtNormalize": "thanh oai ha noi", "preWardNormalize": "xa kim thu thanh oai ha noi", "lat": 20.8374731, "lon": 105.7645561, "geolocation": {"latitude": 20.8374731, "longitude": 105.7645561}}, {"district": "Thanh Oai", "ward": "Kim Thư", "street": "Xóm 5", "city": "Hà Nội", "normalize": "xom 5 kim thu thanh oai ha noi", "streetNormalize": "xom 5 kim thu thanh oai ha noi", "wardNormalize": "kim thu thanh oai ha noi", "districtNormalize": "thanh oai ha noi", "preWardNormalize": "xa kim thu thanh oai ha noi", "lat": 20.8383355, "lon": 105.7652857, "geolocation": {"latitude": 20.8383355, "longitude": 105.7652857}}, {"district": "Thanh Oai", "ward": "Kim Thư", "street": "Xóm Dưới", "city": "Hà Nội", "normalize": "xom duoi kim thu thanh oai ha noi", "streetNormalize": "xom duoi kim thu thanh oai ha noi", "wardNormalize": "kim thu thanh oai ha noi", "districtNormalize": "thanh oai ha noi", "preWardNormalize": "xa kim thu thanh oai ha noi", "lat": 20.8395602, "lon": 105.7672195, "geolocation": {"latitude": 20.8395602, "longitude": 105.7672195}}, {"district": "Thanh Oai", "ward": "Kim Thư", "street": "Xóm Giữa", "city": "Hà Nội", "normalize": "xom giua kim thu thanh oai ha noi", "streetNormalize": "xom giua kim thu thanh oai ha noi", "wardNormalize": "kim thu thanh oai ha noi", "districtNormalize": "thanh oai ha noi", "preWardNormalize": "xa kim thu thanh oai ha noi", "lat": 20.8403553, "lon": 105.7661789, "geolocation": {"latitude": 20.8403553, "longitude": 105.7661789}}, {"district": "Thanh Oai", "ward": "Kim Thư", "street": "Xóm Thông", "city": "Hà Nội", "normalize": "xom thong kim thu thanh oai ha noi", "streetNormalize": "xom thong kim thu thanh oai ha noi", "wardNormalize": "kim thu thanh oai ha noi", "districtNormalize": "thanh oai ha noi", "preWardNormalize": "xa kim thu thanh oai ha noi", "lat": 20.8415186, "lon": 105.7658409, "geolocation": {"latitude": 20.8415186, "longitude": 105.7658409}}, {"district": "Thanh Oai", "ward": "Kim Thư", "street": "Đê Tả Đáy", "city": "Hà Nội", "normalize": "de ta day kim thu thanh oai ha noi", "streetNormalize": "de ta day kim thu thanh oai ha noi", "wardNormalize": "kim thu thanh oai ha noi", "districtNormalize": "thanh oai ha noi", "preWardNormalize": "xa kim thu thanh oai ha noi", "lat": 20.8430808, "lon": 105.764088, "geolocation": {"latitude": 20.8430808, "longitude": 105.764088}}, {"district": "Thanh Oai", "ward": "Liên Châu", "street": "Đường Trục Phía Nam", "city": "Hà Nội", "normalize": "duong truc phia nam lien chau thanh oai ha noi", "streetNormalize": "duong truc phia nam lien chau thanh oai ha noi", "wardNormalize": "lien chau thanh oai ha noi", "districtNormalize": "thanh oai ha noi", "preWardNormalize": "xa lien chau thanh oai ha noi", "lat": 20.8495625, "lon": 105.8022895, "geolocation": {"latitude": 20.8495625, "longitude": 105.8022895}}, {"district": "Thanh Oai", "ward": "Mỹ Hưng", "street": "Sông Ái", "city": "Hà Nội", "normalize": "song ai my hung thanh oai ha noi", "streetNormalize": "song ai my hung thanh oai ha noi", "wardNormalize": "my hung thanh oai ha noi", "districtNormalize": "thanh oai ha noi", "preWardNormalize": "xa my hung thanh oai ha noi", "lat": 20.8949853, "lon": 105.7985394, "geolocation": {"latitude": 20.8949853, "longitude": 105.7985394}}, {"district": "Thanh Oai", "ward": "Mỹ Hưng", "street": "Thạch Nham", "city": "Hà Nội", "normalize": "thach nham my hung thanh oai ha noi", "streetNormalize": "thach nham my hung thanh oai ha noi", "wardNormalize": "my hung thanh oai ha noi", "districtNormalize": "thanh oai ha noi", "preWardNormalize": "xa my hung thanh oai ha noi", "lat": 20.9037363, "lon": 105.8039173, "geolocation": {"latitude": 20.9037363, "longitude": 105.8039173}}, {"district": "Thanh Oai", "ward": "Mỹ Hưng", "street": "Trục Xã", "city": "Hà Nội", "normalize": "truc xa my hung thanh oai ha noi", "streetNormalize": "truc xa my hung thanh oai ha noi", "wardNormalize": "my hung thanh oai ha noi", "districtNormalize": "thanh oai ha noi", "preWardNormalize": "xa my hung thanh oai ha noi", "lat": 20.9104416, "lon": 105.7962752, "geolocation": {"latitude": 20.9104416, "longitude": 105.7962752}}, {"district": "Thanh Oai", "ward": "Mỹ Hưng", "street": "Xóm Chùa", "city": "Hà Nội", "normalize": "xom chua my hung thanh oai ha noi", "streetNormalize": "xom chua my hung thanh oai ha noi", "wardNormalize": "my hung thanh oai ha noi", "districtNormalize": "thanh oai ha noi", "preWardNormalize": "xa my hung thanh oai ha noi", "lat": 20.9094572, "lon": 105.7985399, "geolocation": {"latitude": 20.9094572, "longitude": 105.7985399}}, {"district": "Thanh Oai", "ward": "Mỹ Hưng", "street": "Đường Sái", "city": "Hà Nội", "normalize": "duong sai my hung thanh oai ha noi", "streetNormalize": "duong sai my hung thanh oai ha noi", "wardNormalize": "my hung thanh oai ha noi", "districtNormalize": "thanh oai ha noi", "preWardNormalize": "xa my hung thanh oai ha noi", "lat": 20.9043491, "lon": 105.785964, "geolocation": {"latitude": 20.9043491, "longitude": 105.785964}}, {"district": "Thanh Oai", "ward": "Mỹ Hưng", "street": "Đường Trục Phía Nam", "city": "Hà Nội", "normalize": "duong truc phia nam my hung thanh oai ha noi", "streetNormalize": "duong truc phia nam my hung thanh oai ha noi", "wardNormalize": "my hung thanh oai ha noi", "districtNormalize": "thanh oai ha noi", "preWardNormalize": "xa my hung thanh oai ha noi", "lat": 20.8495625, "lon": 105.8022895, "geolocation": {"latitude": 20.8495625, "longitude": 105.8022895}}, {"district": "Thanh Oai", "ward": "Phương Trung", "street": "Quốc Lộ 21b", "city": "Hà Nội", "normalize": "quoc lo 21b phuong trung thanh oai ha noi", "streetNormalize": "quoc lo 21b phuong trung thanh oai ha noi", "wardNormalize": "phuong trung thanh oai ha noi", "districtNormalize": "thanh oai ha noi", "preWardNormalize": "xa phuong trung thanh oai ha noi", "lat": 20.853637, "lon": 105.7684941, "geolocation": {"latitude": 20.853637, "longitude": 105.7684941}}, {"district": "Thanh Oai", "ward": "Phương Trung", "street": "Trạm Bơm", "city": "Hà Nội", "normalize": "tram bom phuong trung thanh oai ha noi", "streetNormalize": "tram bom phuong trung thanh oai ha noi", "wardNormalize": "phuong trung thanh oai ha noi", "districtNormalize": "thanh oai ha noi", "preWardNormalize": "xa phuong trung thanh oai ha noi", "lat": 20.8323537, "lon": 105.7650977, "geolocation": {"latitude": 20.8323537, "longitude": 105.7650977}}, {"district": "Thanh Oai", "ward": "Phương Trung", "street": "Đê Tả Đáy", "city": "Hà Nội", "normalize": "de ta day phuong trung thanh oai ha noi", "streetNormalize": "de ta day phuong trung thanh oai ha noi", "wardNormalize": "phuong trung thanh oai ha noi", "districtNormalize": "thanh oai ha noi", "preWardNormalize": "xa phuong trung thanh oai ha noi", "lat": 20.827679, "lon": 105.7603115, "geolocation": {"latitude": 20.827679, "longitude": 105.7603115}}, {"district": "Thanh Oai", "ward": "Tam Hưng", "street": "Bình Minh", "city": "Hà Nội", "normalize": "binh minh tam hung thanh oai ha noi", "streetNormalize": "binh minh tam hung thanh oai ha noi", "wardNormalize": "tam hung thanh oai ha noi", "districtNormalize": "thanh oai ha noi", "preWardNormalize": "xa tam hung thanh oai ha noi", "lat": 20.8988368, "lon": 105.7870925, "geolocation": {"latitude": 20.8988368, "longitude": 105.7870925}}, {"district": "Thanh Oai", "ward": "Tam Hưng", "street": "Bùi Xá", "city": "Hà Nội", "normalize": "bui xa tam hung thanh oai ha noi", "streetNormalize": "bui xa tam hung thanh oai ha noi", "wardNormalize": "tam hung thanh oai ha noi", "districtNormalize": "thanh oai ha noi", "preWardNormalize": "xa tam hung thanh oai ha noi", "lat": 20.8672379, "lon": 105.7953224, "geolocation": {"latitude": 20.8672379, "longitude": 105.7953224}}, {"district": "Thanh Oai", "ward": "Tam Hưng", "street": "Cổng Làng", "city": "Hà Nội", "normalize": "cong lang tam hung thanh oai ha noi", "streetNormalize": "cong lang tam hung thanh oai ha noi", "wardNormalize": "tam hung thanh oai ha noi", "districtNormalize": "thanh oai ha noi", "preWardNormalize": "xa tam hung thanh oai ha noi", "lat": 20.8881255, "lon": 105.7823116, "geolocation": {"latitude": 20.8881255, "longitude": 105.7823116}}, {"district": "Thanh Oai", "ward": "Tam Hưng", "street": "Ngô Long", "city": "Hà Nội", "normalize": "ngo long tam hung thanh oai ha noi", "streetNormalize": "ngo long tam hung thanh oai ha noi", "wardNormalize": "tam hung thanh oai ha noi", "districtNormalize": "thanh oai ha noi", "preWardNormalize": "xa tam hung thanh oai ha noi", "lat": 20.8903018, "lon": 105.7746823, "geolocation": {"latitude": 20.8903018, "longitude": 105.7746823}}, {"district": "Thanh Oai", "ward": "Tam Hưng", "street": "Sau Làng", "city": "Hà Nội", "normalize": "sau lang tam hung thanh oai ha noi", "streetNormalize": "sau lang tam hung thanh oai ha noi", "wardNormalize": "tam hung thanh oai ha noi", "districtNormalize": "thanh oai ha noi", "preWardNormalize": "xa tam hung thanh oai ha noi", "lat": 20.8900591, "lon": 105.7833571, "geolocation": {"latitude": 20.8900591, "longitude": 105.7833571}}, {"district": "Thanh Oai", "ward": "Tam Hưng", "street": "Sông Ái", "city": "Hà Nội", "normalize": "song ai tam hung thanh oai ha noi", "streetNormalize": "song ai tam hung thanh oai ha noi", "wardNormalize": "tam hung thanh oai ha noi", "districtNormalize": "thanh oai ha noi", "preWardNormalize": "xa tam hung thanh oai ha noi", "lat": 20.8870824, "lon": 105.7895518, "geolocation": {"latitude": 20.8870824, "longitude": 105.7895518}}, {"district": "Thanh Oai", "ward": "Tam Hưng", "street": "Tam Hưng", "city": "Hà Nội", "normalize": "tam hung tam hung thanh oai ha noi", "streetNormalize": "tam hung tam hung thanh oai ha noi", "wardNormalize": "tam hung thanh oai ha noi", "districtNormalize": "thanh oai ha noi", "preWardNormalize": "xa tam hung thanh oai ha noi", "lat": 20.8813669, "lon": 105.7857394, "geolocation": {"latitude": 20.8813669, "longitude": 105.7857394}}, {"district": "Thanh Oai", "ward": "Tam Hưng", "street": "Thanh Niên", "city": "Hà Nội", "normalize": "thanh nien tam hung thanh oai ha noi", "streetNormalize": "thanh nien tam hung thanh oai ha noi", "wardNormalize": "tam hung thanh oai ha noi", "districtNormalize": "thanh oai ha noi", "preWardNormalize": "xa tam hung thanh oai ha noi", "lat": 20.8886142, "lon": 105.7787979, "geolocation": {"latitude": 20.8886142, "longitude": 105.7787979}}, {"district": "Thanh Oai", "ward": "Tam Hưng", "street": "Tê Quả", "city": "Hà Nội", "normalize": "te qua tam hung thanh oai ha noi", "streetNormalize": "te qua tam hung thanh oai ha noi", "wardNormalize": "tam hung thanh oai ha noi", "districtNormalize": "thanh oai ha noi", "preWardNormalize": "xa tam hung thanh oai ha noi", "lat": 20.8896199, "lon": 105.7790271, "geolocation": {"latitude": 20.8896199, "longitude": 105.7790271}}, {"district": "Thanh Oai", "ward": "Tam Hưng", "street": "Văn Khê", "city": "Hà Nội", "normalize": "van khe tam hung thanh oai ha noi", "streetNormalize": "van khe tam hung thanh oai ha noi", "wardNormalize": "tam hung thanh oai ha noi", "districtNormalize": "thanh oai ha noi", "preWardNormalize": "xa tam hung thanh oai ha noi", "lat": 20.8692932, "lon": 105.7893362, "geolocation": {"latitude": 20.8692932, "longitude": 105.7893362}}, {"district": "Thanh Oai", "ward": "Tam Hưng", "street": "Đt 427b", "city": "Hà Nội", "normalize": "dt 427b tam hung thanh oai ha noi", "streetNormalize": "dt 427b tam hung thanh oai ha noi", "wardNormalize": "tam hung thanh oai ha noi", "districtNormalize": "thanh oai ha noi", "preWardNormalize": "xa tam hung thanh oai ha noi", "lat": 20.8775244, "lon": 105.7956711, "geolocation": {"latitude": 20.8775244, "longitude": 105.7956711}}, {"district": "Thanh Oai", "ward": "Tam Hưng", "street": "Đường Chảy", "city": "Hà Nội", "normalize": "duong chay tam hung thanh oai ha noi", "streetNormalize": "duong chay tam hung thanh oai ha noi", "wardNormalize": "tam hung thanh oai ha noi", "districtNormalize": "thanh oai ha noi", "preWardNormalize": "xa tam hung thanh oai ha noi", "lat": 20.8888353, "lon": 105.7762414, "geolocation": {"latitude": 20.8888353, "longitude": 105.7762414}}, {"district": "Thanh Oai", "ward": "Tam Hưng", "street": "Đường Muỗi", "city": "Hà Nội", "normalize": "duong muoi tam hung thanh oai ha noi", "streetNormalize": "duong muoi tam hung thanh oai ha noi", "wardNormalize": "tam hung thanh oai ha noi", "districtNormalize": "thanh oai ha noi", "preWardNormalize": "xa tam hung thanh oai ha noi", "lat": 20.8722399, "lon": 105.785052, "geolocation": {"latitude": 20.8722399, "longitude": 105.785052}}, {"district": "Thanh Oai", "ward": "Tam Hưng", "street": "Đường Sái", "city": "Hà Nội", "normalize": "duong sai tam hung thanh oai ha noi", "streetNormalize": "duong sai tam hung thanh oai ha noi", "wardNormalize": "tam hung thanh oai ha noi", "districtNormalize": "thanh oai ha noi", "preWardNormalize": "xa tam hung thanh oai ha noi", "lat": 20.8990234841023, "lon": 105.785401903637, "geolocation": {"latitude": 20.8990234841023, "longitude": 105.785401903637}}, {"district": "Thanh Oai", "ward": "Tam Hưng", "street": "Đường Trục Phía Nam", "city": "Hà Nội", "normalize": "duong truc phia nam tam hung thanh oai ha noi", "streetNormalize": "duong truc phia nam tam hung thanh oai ha noi", "wardNormalize": "tam hung thanh oai ha noi", "districtNormalize": "thanh oai ha noi", "preWardNormalize": "xa tam hung thanh oai ha noi", "lat": 20.8495625, "lon": 105.8022895, "geolocation": {"latitude": 20.8495625, "longitude": 105.8022895}}, {"district": "Thanh Oai", "ward": "Tam Hưng", "street": "Đại Thắng", "city": "Hà Nội", "normalize": "dai thang tam hung thanh oai ha noi", "streetNormalize": "dai thang tam hung thanh oai ha noi", "wardNormalize": "tam hung thanh oai ha noi", "districtNormalize": "thanh oai ha noi", "preWardNormalize": "xa tam hung thanh oai ha noi", "lat": 20.8909638, "lon": 105.778945, "geolocation": {"latitude": 20.8909638, "longitude": 105.778945}}, {"district": "Thanh Oai", "ward": "Tân Ước", "street": "Liên Thôn Xã", "city": "Hà Nội", "normalize": "lien thon xa tan uoc thanh oai ha noi", "streetNormalize": "lien thon xa tan uoc thanh oai ha noi", "wardNormalize": "tan uoc thanh oai ha noi", "districtNormalize": "thanh oai ha noi", "preWardNormalize": "xa tan uoc thanh oai ha noi", "lat": 20.8285854, "lon": 105.8015308, "geolocation": {"latitude": 20.8285854, "longitude": 105.8015308}}, {"district": "Thanh Oai", "ward": "Tân Ước", "street": "Đường Trục Phía Nam", "city": "Hà Nội", "normalize": "duong truc phia nam tan uoc thanh oai ha noi", "streetNormalize": "duong truc phia nam tan uoc thanh oai ha noi", "wardNormalize": "tan uoc thanh oai ha noi", "districtNormalize": "thanh oai ha noi", "preWardNormalize": "xa tan uoc thanh oai ha noi", "lat": 20.8267134, "lon": 105.8167239, "geolocation": {"latitude": 20.8267134, "longitude": 105.8167239}}, {"district": "Thanh Oai", "ward": "Thanh Cao", "street": "10/3", "city": "Hà Nội", "normalize": "10/3 thanh cao thanh oai ha noi", "streetNormalize": "10/3 thanh cao thanh oai ha noi", "wardNormalize": "thanh cao thanh oai ha noi", "districtNormalize": "thanh oai ha noi", "preWardNormalize": "xa thanh cao thanh oai ha noi", "lat": 20.8888338, "lon": 105.7612926, "geolocation": {"latitude": 20.8888338, "longitude": 105.7612926}}, {"district": "Thanh Oai", "ward": "Thanh Cao", "street": "Bình Minh Thanh Cao", "city": "Hà Nội", "normalize": "binh minh thanh cao thanh cao thanh oai ha noi", "streetNormalize": "binh minh thanh cao thanh cao thanh oai ha noi", "wardNormalize": "thanh cao thanh oai ha noi", "districtNormalize": "thanh oai ha noi", "preWardNormalize": "xa thanh cao thanh oai ha noi", "lat": 20.8852236, "lon": 105.752835, "geolocation": {"latitude": 20.8852236, "longitude": 105.752835}}, {"district": "Thanh Oai", "ward": "Thanh Cao", "street": "Liên Thôn", "city": "Hà Nội", "normalize": "lien thon thanh cao thanh oai ha noi", "streetNormalize": "lien thon thanh cao thanh oai ha noi", "wardNormalize": "thanh cao thanh oai ha noi", "districtNormalize": "thanh oai ha noi", "preWardNormalize": "xa thanh cao thanh oai ha noi", "lat": 20.8908444, "lon": 105.7563032, "geolocation": {"latitude": 20.8908444, "longitude": 105.7563032}}, {"district": "Thanh Oai", "ward": "Thanh Cao", "street": "Đê Tả Đáy", "city": "Hà Nội", "normalize": "de ta day thanh cao thanh oai ha noi", "streetNormalize": "de ta day thanh cao thanh oai ha noi", "wardNormalize": "thanh cao thanh oai ha noi", "districtNormalize": "thanh oai ha noi", "preWardNormalize": "xa thanh cao thanh oai ha noi", "lat": 20.8622941, "lon": 105.7444443, "geolocation": {"latitude": 20.8622941, "longitude": 105.7444443}}, {"district": "Thanh Oai", "ward": "Thanh Cao", "street": "Đường Mương", "city": "Hà Nội", "normalize": "duong muong thanh cao thanh oai ha noi", "streetNormalize": "duong muong thanh cao thanh oai ha noi", "wardNormalize": "thanh cao thanh oai ha noi", "districtNormalize": "thanh oai ha noi", "preWardNormalize": "xa thanh cao thanh oai ha noi", "lat": 20.8890748, "lon": 105.7598832, "geolocation": {"latitude": 20.8890748, "longitude": 105.7598832}}, {"district": "Thanh Oai", "ward": "Thanh Mai", "street": "Quốc Lộ 21b", "city": "Hà Nội", "normalize": "quoc lo 21b thanh mai thanh oai ha noi", "streetNormalize": "quoc lo 21b thanh mai thanh oai ha noi", "wardNormalize": "thanh mai thanh oai ha noi", "districtNormalize": "thanh oai ha noi", "preWardNormalize": "xa thanh mai thanh oai ha noi", "lat": 20.8717743, "lon": 105.7586251, "geolocation": {"latitude": 20.8717743, "longitude": 105.7586251}}, {"district": "Thanh Oai", "ward": "Thanh Mai", "street": "Đê Tả Đáy", "city": "Hà Nội", "normalize": "de ta day thanh mai thanh oai ha noi", "streetNormalize": "de ta day thanh mai thanh oai ha noi", "wardNormalize": "thanh mai thanh oai ha noi", "districtNormalize": "thanh oai ha noi", "preWardNormalize": "xa thanh mai thanh oai ha noi", "lat": 20.8622941, "lon": 105.7444443, "geolocation": {"latitude": 20.8622941, "longitude": 105.7444443}}, {"district": "Thanh Oai", "ward": "Thanh Thùy", "street": "Bùi Xá", "city": "Hà Nội", "normalize": "bui xa thanh thuy thanh oai ha noi", "streetNormalize": "bui xa thanh thuy thanh oai ha noi", "wardNormalize": "thanh thuy thanh oai ha noi", "districtNormalize": "thanh oai ha noi", "preWardNormalize": "xa thanh thuy thanh oai ha noi", "lat": 20.8733088081129, "lon": 105.801363605518, "geolocation": {"latitude": 20.8733088081129, "longitude": 105.801363605518}}, {"district": "Thanh Oai", "ward": "Thanh Thùy", "street": "Liên Thôn Xã", "city": "Hà Nội", "normalize": "lien thon xa thanh thuy thanh oai ha noi", "streetNormalize": "lien thon xa thanh thuy thanh oai ha noi", "wardNormalize": "thanh thuy thanh oai ha noi", "districtNormalize": "thanh oai ha noi", "preWardNormalize": "xa thanh thuy thanh oai ha noi", "lat": 20.8614762411842, "lon": 105.812930947941, "geolocation": {"latitude": 20.8614762411842, "longitude": 105.812930947941}}, {"district": "Thanh Oai", "ward": "Thanh Thùy", "street": "Đt 427b", "city": "Hà Nội", "normalize": "dt 427b thanh thuy thanh oai ha noi", "streetNormalize": "dt 427b thanh thuy thanh oai ha noi", "wardNormalize": "thanh thuy thanh oai ha noi", "districtNormalize": "thanh oai ha noi", "preWardNormalize": "xa thanh thuy thanh oai ha noi", "lat": 20.8775244, "lon": 105.7956711, "geolocation": {"latitude": 20.8775244, "longitude": 105.7956711}}, {"district": "Thanh Oai", "ward": "Thanh Thùy", "street": "Đường Trục Phía Nam", "city": "Hà Nội", "normalize": "duong truc phia nam thanh thuy thanh oai ha noi", "streetNormalize": "duong truc phia nam thanh thuy thanh oai ha noi", "wardNormalize": "thanh thuy thanh oai ha noi", "districtNormalize": "thanh oai ha noi", "preWardNormalize": "xa thanh thuy thanh oai ha noi", "lat": 20.8689357, "lon": 105.8049172, "geolocation": {"latitude": 20.8689357, "longitude": 105.8049172}}, {"district": "Thanh Oai", "ward": "Thanh Văn", "street": "Liên Thôn Xã", "city": "Hà Nội", "normalize": "lien thon xa thanh van thanh oai ha noi", "streetNormalize": "lien thon xa thanh van thanh oai ha noi", "wardNormalize": "thanh van thanh oai ha noi", "districtNormalize": "thanh oai ha noi", "preWardNormalize": "xa thanh van thanh oai ha noi", "lat": 20.8514468, "lon": 105.8127317, "geolocation": {"latitude": 20.8514468, "longitude": 105.8127317}}, {"district": "Thanh Oai", "ward": "Thanh Văn", "street": "Đường Trục Phía Nam", "city": "Hà Nội", "normalize": "duong truc phia nam thanh van thanh oai ha noi", "streetNormalize": "duong truc phia nam thanh van thanh oai ha noi", "wardNormalize": "thanh van thanh oai ha noi", "districtNormalize": "thanh oai ha noi", "preWardNormalize": "xa thanh van thanh oai ha noi", "lat": 20.8508155, "lon": 105.8019096, "geolocation": {"latitude": 20.8508155, "longitude": 105.8019096}}, {"district": "Thanh Oai", "ward": "Xuân Dương", "street": "Đt 429", "city": "Hà Nội", "normalize": "dt 429 xuan duong thanh oai ha noi", "streetNormalize": "dt 429 xuan duong thanh oai ha noi", "wardNormalize": "xuan duong thanh oai ha noi", "districtNormalize": "thanh oai ha noi", "preWardNormalize": "xa xuan duong thanh oai ha noi", "lat": 20.8040687, "lon": 105.7429639, "geolocation": {"latitude": 20.8040687, "longitude": 105.7429639}}]}